matricks/__init__.py
matricks/exceptions.py
matricks/matrix.py
matricks/ops.py
matricks/py.typed
matricks/tools.py
matricks/types.py
swift_matrix-0.1.0.dist-info/licenses/LICENSE
swift_matrix-0.1.0.dist-info/METADATA
swift_matrix-0.1.0.dist-info/WHEEL
swift_matrix-0.1.0.dist-info/top_level.txt
swift_matrix-0.1.0.dist-info/RECORD
