Metadata-Version: 2.4
Name: swift-matrix
Version: 0.1.0
Summary: Lightweight matrix library with a tiny immutable Matrix class.
Home-page: https://github.com/El3k0n/Matrix
Author: Steve Torn
Author-email: ваш@email.com
License: MIT
Project-URL: Homepage, https://github.com/El3k0n/Matrix
Project-URL: Issues, https://github.com/El3k0n/Matrix/issues
Requires-Python: >=3.8
License-File: LICENSE
Requires-Dist: requests
Dynamic: license-file
Dynamic: requires-dist
